src/receiver_FSM.sv
module receiver_FSM(
    input logic clk, nrst,
    input logic baud_tick, data_i, parity_en_i,
    output logic shift_en, parity_en, frame_en,
    output logic data_ready
);
    // typedef enum logic [2:0]{
    //     IDLE = 0,
    //     START = 1,
    //     DATA = 2,
    //     PARITY = 3,
    //     STOP = 4
    // } state_t;

    logic [2:0] state, nextState;
    logic [3:0] bit_count, nextCount;

    always_ff @(posedge clk, negedge nrst) begin
        if(~nrst) begin
            state <= 3'd0;
            bit_count <= '0;
        end else begin  
            state <= nextState;
            bit_count <= nextCount;
        end
    end

    always_comb begin
        shift_en = 1'b0;
        parity_en = 1'b0;
        frame_en = 1'b0;
        data_ready = 1'b0;
        nextState = state;
        nextCount = bit_count;

        case(state)
            3'd0: begin //IDLE
                nextCount = '0;
                if (data_i == 1'b0) begin nextState = 3'd1; end
                else begin nextState = 3'd0; end
            end
            3'd1: begin //START
                if (baud_tick == 1'b0) begin
                    nextState = 3'd1;
                end else if (baud_tick == 1'b1 && data_i == 1'b0) begin 
                    nextState = 3'd2; 
                    nextCount = '0;
                end
                else if(baud_tick == 1'b1 && data_i == 1'b1) begin 
                    nextState = 3'd0; 
                end
            end    
            3'd2: begin //DATA
                if (baud_tick == 1'b1 && bit_count == 4'd7 && parity_en_i == 1'b1) begin
                    shift_en = 1'b1;
                    nextState = 3'd3;
                    nextCount = '0;
                end else if (baud_tick == 1'b1 && bit_count < 4'd7) begin
                    shift_en = 1'b1;
                    nextState = 3'd2;
                    nextCount = bit_count + 4'd1;
                end else if (baud_tick == 1'b1 && bit_count == 4'd7 && parity_en_i == 1'b0) begin
                    shift_en = 1'b1;
                    nextState = 3'd4;
                    nextCount = '0;
                end else if (baud_tick == 1'b0) begin
                    nextState = 3'd2;
                end
            end
            3'd3: begin //PARITY
                if (baud_tick == 1'b0) begin
                    nextState = 3'd3;
                end else begin
                    parity_en = 1'b1;
                    nextState = 3'd4;
                end
            end
            3'd4: begin //STOP
                if (baud_tick == 1'b0) begin
                    nextState = 3'd4;
                end else begin
                    frame_en = 1'b1;
                    data_ready = 1'b1;
                    nextState = 3'd0;
                end
            end
            default: begin nextState = 3'd0; end
        endcase
    end

endmodule

testbench/receiver_FSM_tb.sv
`timescale 1ns/1ps

module receiver_FSM_tb();

logic clk, nrst, baud_tick, data_i, parity_en_i;
logic shift_en, parity_en, frame_en, data_ready;

receiver_FSM FSMTest(
    .clk(clk),
    .nrst(nrst),
    .baud_tick(baud_tick),
    .data_i(data_i),
    .parity_en_i(parity_en_i),
    .shift_en(shift_en),
    .parity_en(parity_en),
    .frame_en(frame_en),
    .data_ready(data_ready)
);

always begin
    #10
    clk = ~clk;
end

initial begin
    $dumpfile("receiver_FSM.vcd");
    $dumpvars(0, receiver_FSM_tb);
    clk = 0;
    baud_tick = 0;

    //reset
    nrst = 1;
    #10
    nrst = 0;
    #10
    nrst = 1;
    #20

    parity_en_i = 1; 
    data_i = 1; 
    #40
    
    //start bit
    data_i = 0;
    #20
    baud_tick = 1;
    #20
    baud_tick = 0;
    #20
    
    //data bits -> 10100101
    data_i = 1; 
    #20
    baud_tick = 1;
    #20
    baud_tick = 0;
    #20
    
    data_i = 0; 
    #20
    baud_tick = 1;
    #20
    baud_tick = 0;
    #20
    
    data_i = 1;
    #20
    baud_tick = 1;
    #20
    baud_tick = 0;
    #20
    
    data_i = 0; 
    #20
    baud_tick = 1;
    #20
    baud_tick = 0;
    #20
    
    data_i = 0; 
    #20
    baud_tick = 1;
    #20
    baud_tick = 0;
    #20
    
    data_i = 1; 
    #20
    baud_tick = 1;
    #20
    baud_tick = 0;
    #20
    
    data_i = 0;
    #20
    baud_tick = 1;
    #20
    baud_tick = 0;
    #20
    
    data_i = 1; 
    #20
    baud_tick = 1;
    #20
    baud_tick = 0;
    #20
    
    //parity bit
    data_i = 1; //odd parity for 10100101
    #20
    baud_tick = 1;
    #20
    baud_tick = 0;
    #20
    
    //stop bit
    data_i = 1;
    #20
    baud_tick = 1;
    #20
    baud_tick = 0;
    #20

    #100
    $finish;
end
endmodule

waveforms/receiver_FSM.vcd
$date
	Mon Dec  1 03:14:58 2025
$end
$version
	Icarus Verilog
$end
$timescale
	1ps
$end
$scope module receiver_FSM_tb $end
$var wire 1 ! shift_en $end
$var wire 1 " parity_en $end
$var wire 1 # frame_en $end
$var wire 1 $ data_ready $end
$var reg 1 % baud_tick $end
$var reg 1 & clk $end
$var reg 1 ' data_i $end
$var reg 1 ( nrst $end
$var reg 1 ) parity_en_i $end
$scope module FSMTest $end
$var wire 1 % baud_tick $end
$var wire 1 & clk $end
$var wire 1 ' data_i $end
$var wire 1 ( nrst $end
$var wire 1 ) parity_en_i $end
$var reg 4 * bit_count [3:0] $end
$var reg 1 $ data_ready $end
$var reg 1 # frame_en $end
$var reg 4 + nextCount [3:0] $end
$var reg 3 , nextState [2:0] $end
$var reg 1 " parity_en $end
$var reg 1 ! shift_en $end
$var reg 3 - state [2:0] $end
$upscope $end
$upscope $end
$enddefinitions $end
$comment Show the parameter values. $end
$dumpall
$end
#0
$dumpvars
b0 -
b0 ,
b0 +
bx *
x)
1(
x'
0&
0%
0$
0#
0"
0!
$end
#10000
b0 *
0(
1&
#20000
1(
0&
#30000
1&
#40000
0&
1'
1)
#50000
1&
#60000
0&
#70000
1&
#80000
b1 ,
0&
0'
#90000
b1 -
1&
#100000
b10 ,
0&
1%
#110000
b1 +
1!
b10 -
1&
#120000
b0 +
0!
0&
0%
#130000
1&
#140000
0&
1'
#150000
1&
#160000
b1 +
1!
0&
1%
#170000
b10 +
1!
b1 *
1&
#180000
b1 +
0!
0&
0%
#190000
1&
#200000
0&
0'
#210000
1&
#220000
b10 +
1!
0&
1%
#230000
b11 +
1!
b10 *
1&
#240000
b10 +
0!
0&
0%
#250000
1&
#260000
0&
1'
#270000
1&
#280000
b11 +
1!
0&
1%
#290000
b100 +
1!
b11 *
1&
#300000
b11 +
0!
0&
0%
#310000
1&
#320000
0&
0'
#330000
1&
#340000
b100 +
1!
0&
1%
#350000
b101 +
1!
b100 *
1&
#360000
b100 +
0!
0&
0%
#370000
1&
#380000
0&
#390000
1&
#400000
b101 +
1!
0&
1%
#410000
b110 +
1!
b101 *
1&
#420000
b101 +
0!
0&
0%
#430000
1&
#440000
0&
1'
#450000
1&
#460000
b110 +
1!
0&
1%
#470000
b111 +
1!
b110 *
1&
#480000
b110 +
0!
0&
0%
#490000
1&
#500000
0&
0'
#510000
1&
#520000
b111 +
1!
0&
1%
#530000
b0 +
b11 ,
1!
b111 *
1&
#540000
b111 +
b10 ,
0!
0&
0%
#550000
1&
#560000
0&
1'
#570000
1&
#580000
b0 +
b11 ,
1!
0&
1%
#590000
b100 ,
1"
0!
b0 *
b11 -
1&
#600000
b11 ,
0"
0&
0%
#610000
1&
#620000
0&
#630000
1&
#640000
b100 ,
1"
0&
1%
#650000
b0 ,
1$
1#
0"
b100 -
1&
#660000
b100 ,
0$
0#
0&
0%
#670000
1&
#680000
0&
#690000
1&
#700000
b0 ,
1$
1#
0&
1%
#710000
0$
0#
b0 -
1&
#720000
0&
0%
