source/transmitterMux.sv
module transmitterMux(
    input logic piso_i, start, stop, parity_i,
    input logic [1:0] select,
    output logic tx_data_o
);
    always_comb begin
        if(select == 2'b00) begin
            tx_data_o = start;
        end else if (select == 2'b01) begin
            tx_data_o = piso_i;
        end else if (select == 2'b10) begin
            tx_data_o = parity_i;
        end else begin //select =  11
            tx_data_o = stop; 
        end
    end

endmodule

testbench/transmitterMux_tb.sv
`timescale 1ns / 1ps

module transmitterMux_tb();

logic piso_i, start, stop, parity_i;
logic [1:0] select;
logic tx_data_o;

transmitterMux muxTest(
    .piso_i(piso_i),
    .start(start),
    .stop(stop),
    .parity_i(parity_i),
    .select(select),
    .tx_data_o(tx_data_o)
);

initial begin
    $dumpfile("transmitterMux.vcd");
    $dumpvars(0, transmitterMux_tb);

    select = '0;
    piso_i = 1;
    start = 1;
    stop = 1;
    parity_i = 1;
    #10

    //test 00
    select = 2'b00;
    #10
    start = 0;
    #10
    start = 1;
    #10
    //test 01
    select = 2'b01;
    #10
    piso_i = 0;
    #10
    piso_i = 1;
    #10
    //test 10
    select = 2'b10;
    #10
    parity_i = 0;
    #10
    parity_i = 1;
    #10
    //test 11
    select = 2'b11;
    #10
    stop = 0;
    #10
    stop = 1;
    #10
    
    #10
    $finish;
end

endmodule

waveforms/transmitterMux.vcd
$date
	Sat Nov 29 20:41:57 2025
$end
$version
	Icarus Verilog
$end
$timescale
	1ps
$end
$scope module transmitterMux_tb $end
$var wire 1 ! tx_data_o $end
$var reg 1 " parity_i $end
$var reg 1 # piso_i $end
$var reg 2 $ select [1:0] $end
$var reg 1 % start $end
$var reg 1 & stop $end
$scope module muxTest $end
$var wire 1 " parity_i $end
$var wire 1 # piso_i $end
$var wire 2 ' select [1:0] $end
$var wire 1 % start $end
$var wire 1 & stop $end
$var reg 1 ! tx_data_o $end
$upscope $end
$upscope $end
$enddefinitions $end
$comment Show the parameter values. $end
$dumpall
$end
#0
$dumpvars
b0 '
1&
1%
b0 $
1#
1"
1!
$end
#20000
0!
0%
#30000
1!
1%
#40000
b1 $
b1 '
#50000
0!
0#
#60000
1!
1#
#70000
b10 $
b10 '
#80000
0"
#90000
1"
#100000
b11 $
b11 '
#110000
0!
0&
#120000
1!
1&
