source/transmitter_PISO.sv
// Transmitter Parallel In Serial Out Module (Shift Register w/ Parallel Load)
// Anna Dalton (https://github.com/annazdalton)

module transmitter_PISO(
    input clk, nrst,
    input logic [7:0] data_i,
    input logic shift_en, load,
    output logic piso_o
);
    logic nextpiso_o;
    logic [7:0] piso_data, nextpiso_data;

    always_ff @(posedge clk, negedge nrst) begin
        if (~nrst) begin
            piso_o <= '0;
            piso_data <= '0;
        end else begin
            piso_o <= nextpiso_o;
            piso_data <= nextpiso_data;
        end
    end

    //shift register logic, parallel load has priority 
    //LSB gets sent out first
    always_comb begin
        if(load) begin
            nextpiso_data = data_i;
            nextpiso_o = piso_o;
        end else if (shift_en) begin
            nextpiso_data = {1'b0, piso_data[7:1]};
            nextpiso_o = piso_data[0];
        end else begin
            nextpiso_data = piso_data;
            nextpiso_o = piso_o;
        end
    end

endmodule

testbench/transmitter_PISO_tb.sv
`timescale 1ns / 1ps

module transmitter_PISO_tb();

logic clk, nrst, shift_en, load, piso_o;
logic [7:0] data_i;

transmitter_PISO PISOTest(
    .clk(clk),
    .nrst(nrst),
    .data_i(data_i),
    .shift_en(shift_en),
    .load(load),
    .piso_o(piso_o)
);

always begin
    #10
    clk = 1'b0;
    #10
    clk = 1'b1;
end

initial begin
    $dumpfile("transmitter_PISO.vcd");
    $dumpvars(0, transmitter_PISO_tb);
    
    clk = 1'b0;

    //reset
    nrst = 1'b1;
    #10
    nrst = 1'b0;
    #10
    nrst = 1'b1;
    
    #10
    data_i = 0110_0101;
    load = 1;
    shift_en = 0;
    #10
    load = 0;
    shift_en = 1;     

    #200
    $finish;
end

endmodule

waveforms/transmitter_PISO.vcd
$date
	Sat Nov 29 22:38:02 2025
$end
$version
	Icarus Verilog
$end
$timescale
	1ps
$end
$scope module transmitter_PISO_tb $end
$var wire 1 ! piso_o $end
$var reg 1 " clk $end
$var reg 8 # data_i [7:0] $end
$var reg 1 $ load $end
$var reg 1 % nrst $end
$var reg 1 & shift_en $end
$scope module PISOTest $end
$var wire 1 " clk $end
$var wire 8 ' data_i [7:0] $end
$var wire 1 $ load $end
$var wire 1 % nrst $end
$var wire 1 & shift_en $end
$var reg 8 ( nextpiso_data [7:0] $end
$var reg 1 ) nextpiso_o $end
$var reg 8 * piso_data [7:0] $end
$var reg 1 ! piso_o $end
$upscope $end
$upscope $end
$enddefinitions $end
$comment Show the parameter values. $end
$dumpall
$end
#0
$dumpvars
bx *
x)
bx (
bx '
x&
1%
x$
bx #
0"
x!
$end
#10000
0)
b0 (
b0 *
0!
0%
#20000
1%
1"
#30000
b1000101 (
0&
1$
b1000101 #
b1000101 '
0"
#40000
1)
b1000101 *
b100010 (
1&
0$
1"
#50000
0"
#60000
0)
b10001 (
b100010 *
1!
1"
#70000
0"
#80000
1)
b1000 (
b10001 *
0!
1"
#90000
0"
#100000
0)
b100 (
b1000 *
1!
1"
#110000
0"
#120000
b10 (
b100 *
0!
1"
#130000
0"
#140000
b1 (
b10 *
1"
#150000
0"
#160000
1)
b0 (
b1 *
1"
#170000
0"
#180000
0)
b0 *
1!
1"
#190000
0"
#200000
0!
1"
