src/baud_generator.sv
module baud_generator(
    input clk, nrst,
    output baud_tick
);
    logic [15:0] counter, divisor, counter_n;
    logic baud_tick_n;
    
    //baud rate currently set to 9600, hwclk is 12MHz
    //divisor = clock_Frequency / baud_Rate

    //change divisor value to change baud rate
    assign divisor = 16'd1250;

    always_ff @(posedge clk, negedge rst_n) begin
        if (~rst_n) begin
            counter   <= 16'd0;
            baud_tick <= 1'b0;
        end else begin
            counter <= counter_n;
            baud_tick <= baud_tick_n;
        end
    end

    always_comb begin
        if(counter == (divisor - 16'd1)) begin
            counter_n = 16'd0;
            baud_tick_n = 1'b1;
        end else begin
            counter_n = counter + 16'd1;
            baud_tick = 1'b0;
        end
    end

endmodule

source/transmitterMux.sv
module transmitterMux(
    input logic piso_i, start, stop, parity_i,
    input logic [1:0] select,
    output logic tx_data_o
);
    always_comb begin
        if(select == 2'b00) begin
            tx_data_o = start;
        end else if (select == 2'b01) begin
            tx_data_o = piso_i;
        end else if (select == 2'b10) begin
            tx_data_o = parity_i;
        end else begin //select =  11
            tx_data_o = stop; 
        end
    end

endmodule

src/transmitter_parityGen.sv
// Transmitter Parity Generator
// Anna Dalton (https://github.com/annazdalton)

module transmitter_parityGen();
    input logic [7:0] data_i,
    input logic parity_en;
    output logic parity_bit

//even parity
always_comb begin
        if (parity_en) begin
            //XOR reduction for parity bit
            parity_bit = ^ data_i;
        end else begin
            parity_bit = 1'b0;
        end
    end
endmodule

source/transmitter_PISO.sv
// Transmitter Parallel In Serial Out Module (Shift Register w/ Parallel Load)
// Anna Dalton (https://github.com/annazdalton)

module transmitter_PISO(
    input clk, nrst,
    input logic [7:0] data_i,
    input logic shift_en, load,
    output logic piso_o
);
    logic nextpiso_o;
    logic [7:0] piso_data, nextpiso_data;

    always_ff @(posedge clk, negedge nrst) begin
        if (~nrst) begin
            piso_o <= '0;
            piso_data <= '0;
        end else begin
            piso_o <= nextpiso_o;
            piso_data <= nextpiso_data;
        end
    end

    //shift register logic, parallel load has priority 
    //LSB gets sent out first
    always_comb begin
        if(load) begin
            nextpiso_data = data_i;
            nextpiso_o = piso_o;
        end else if (shift_en) begin
            nextpiso_data = {1'b0, piso_data[7:1]};
            nextpiso_o = piso_data[0];
        end else begin
            nextpiso_data = piso_data;
            nextpiso_o = piso_o;
        end
    end

endmodule

src/transmitter_FSM.sv
module transmitter_FSM(
    input logic clk, nrst, baud_tick, tx_valid, parity_en,
    input logic [3:0] count_data,
    output logic start, stop, count_en, count_clear, shift_en, load,
    output logic [1:0] select
);

    // typedef enum logic [2:0]{  
    //     IDLE = 0,
    //     LOAD = 1,
    //     START = 2,
    //     DATA = 3,
    //     PARITY = 4,
    //     STOP = 5
    // } state_t;

    //state_t state, nextState;
    logic [2:0] state, nextState;

    always_ff @(posedge clk, negedge nrst) begin
        if(~nrst) begin
            state <= '0; //idle
        end else begin
            state <= nextState;
        end
    end

    always_comb begin
        //defaults to prevent latch
        nextState = state;

        count_en = 1'b0;
        count_clear = 1'b0;

        start = 1'b0;
        stop = 1'b1;

        select = 2'b11;
        load = 1'b0;
        shift_en = 1'b0;

        case(state) 
            3'b0: begin 
                select = 2'b11; // stop/idle
                
                if(tx_valid) begin
                    nextState = 3'd1;
                end else begin
                    nextState = 3'd0;
                end
            end
            3'd1: begin
                load = 1'b1;
                select = 2'b11;
                nextState = 3'd2;
            end
            3'd2: begin 
                select = 2'b00; //send start bit to rx

                if(baud_tick) begin
                    nextState = 3'd3;
                    count_clear = 1'b1; //clear count before data state
                end else begin
                    nextState = 3'd2;
                end
            end
            3'd3: begin 
                //send data serially output from PISO
                select = 2'b01;

                if(baud_tick) begin
                    shift_en = 1'b1;
                    count_en = 1'b1;
                    //if done counting
                    if(count_data == 4'd7) begin
                        //reset counter
                        count_en = 1'b0;
                        count_clear = 1'b1;
                        if(parity_en) begin
                            nextState = 3'd4;
                        end else begin
                            nextState = 3'd5;
                        end
                    end else begin
                        nextState = 3'd3; //keep sending data out
                    end
                end
            end
            3'd4: begin 
                select = 2'b10; //parity output via mux

                if(baud_tick) begin
                    nextState = 3'd5;
                end else begin
                    nextState = 3'd4;
                end
            end
            3'd5: begin 
                select = 2'b11; // send stop to rx

                if(baud_tick) begin
                    nextState = 3'd0;
                end else begin
                    nextState = 3'd5;
                end
            end
            default: begin
                nextState = '0; 
            end
        endcase
    end
endmodule

source/counter.sv
// counter, counts to 8 for transmitter FSM
// Anna Dalton (https://github.com/annazdalton)

module counter(
    input logic clk, nrst, enable, clear,
    output logic [3:0] count,
    output logic overflow_flag
);
    logic [3:0] nextCount;

    always_ff @(posedge clk, negedge ~nrst) begin
        if(~nrst) begin
            count <= '0;
        end else begin
            count <= nextCount;
        end
    end

    always_comb begin
        if(clear) begin
            nextCount = '0;
        end else if(enable) begin
            nextCount = count + 4'd1; 
            //overflow flag is high if count > 8
            if(count == 4'd8) begin
                overflow_flag = 1'b1; 
            end else begin
                overflow_flag = 1'b0;
            end
        end else begin
            nextCount = count;
        end
    end
endmodule

source/transmitter_top.sv
module transmitter_top (
  // I/O ports
  input  logic hwclk, reset, //hwclk = 10 MHz
  input  logic [20:0] pb,
  output logic [7:0] left, right,
         ss7, ss6, ss5, ss4, ss3, ss2, ss1, ss0,
  output logic red, green, blue,

  // UART ports
  output logic [7:0] txdata,
  input  logic [7:0] rxdata,
  output logic txclk, rxclk,
  input  logic txready, rxready
);


logic [7:0] PISOdata_i;
logic [3:0] count_o;
logic [1:0] mux_select;
logic count_enable, count_clear, count_overflow, piso_o, tx_data_o, mux_stop, mux_start, parity_o, tx_valid, parity_en, shift_en, shift_load, baud_tick;

// data going into transmitter is PB[7:0] of FPGA
assign PISOdata_i = pb[7:0];
// data coming out is shown on RIGHT[0]
assign right[0] = tx_data_o;
assign right[1] = parity_en;
assign right[2] = tx_valid;
assign right[3] = baud_tick;
//user inputs
assign tx_valid = pb[19];
assign parity_en = pb[18];

counter count0(
  .clk(hwclk), 
  .nrst(reset), 
  .enable(count_enable), 
  .clear(count_clear), 
  .count(count_o), 
  .overflow_flag()
);

transmitter_FSM trans_FSM(
  //inputs
  .clk(hwclk),
  .nrst(reset),
  .baud_tick(baud_tick),
  .tx_valid(tx_valid),
  .parity_en(parity_en),
  .count_data(count_o),
  //outputs
  .start(mux_start),
  .stop(mux_stop),
  .count_en(count_enable),
  .count_clear(count_clear),
  .shift_en(shift_en),
  .load(shift_load),
  .select(mux_select)
);

transmitter_PISO trans_PISO(
  .clk(hwclk),
  .nrst(reset),
  .data_i(PISOdata_i),
  .shift_en(shift_en),
  .load(shift_load),
  .piso_o(piso_o)
);

transmitter_parityGen trans_parity(
  .data_i(PISOdata_i),
  .parity_en(parity_en),
  .parity_bit(parity_o)
);

transmitterMux trans_mux(
  .piso_i(piso_o),
  .start(mux_start),
  .stop(mux_stop),
  .parity_i(parity_o),
  .select(mux_select),
  .tx_data_o(tx_data_o)
);

baud_generator baud_gen(
  .clk(hwclk),
  .nrst(reset),
  .baud_tick(baud_tick)
);

endmodule

testbench/transmitter_top_tb.sv
`timescale 1ns / 1ps

module transmitter_top_tb();

logic clk, nrst;
logic [19:0] pb;
logic [7:0] right;

transmitter_top topTest(
    .hwclk(clk),
    .reset(nrst),
    .pb(pb),
    .left(),
    .right(right),
    .ss7(),
    .ss6(),
    .ss5(),
    .ss4(),
    .ss3(),
    .ss2(),
    .ss1(),
    .ss0(),
    .txdata(),
    .rxdata(),
    .txclk(),
    .rxclk(),
    .txready(),
    .rxready()
);

//12MHz clk - period is 83.33 ns
always begin
    #41.66
    clk = ~clk;
end

initial begin
    $dumpfile("transmitter_top.vcd");
    $dumpvars(0, transmitter_top_tb);
    clk = 0;

    //reset
    nrst = 1;
    pb = '0;
    #500
    nrst = 0;
    #500
    nrst = 1;
    #500

    pb[7:0] = 8'b10100101;

    // parity_en on pb[18], tx_valid on pb[19]
    pb[18]    = 1'b0; // 0 = no parity, 1 = enable parity
    pb[19]    = 1'b0;

    //assert tx_valid for one clock
    #500;
    pb[19]    = 1'b1; // tx_valid pulse
    #100;
    pb[19]    = 1'b0;

    #2_000_000; // 2 ms in ns
    $finish;
end
endmodule

waveforms/transmitter_top.vcd
$date
	Sun Nov 30 00:06:27 2025
$end
$version
	Icarus Verilog
$end
$timescale
	1ps
$end
$scope module transmitter_top_tb $end
$var wire 8 ! right [7:0] $end
$var reg 1 " clk $end
$var reg 1 # nrst $end
$var reg 20 $ pb [19:0] $end
$scope module topTest $end
$var wire 1 " hwclk $end
$var wire 21 % pb [20:0] $end
$var wire 1 # reset $end
$var wire 8 & rxdata [7:0] $end
$var wire 1 ' rxready $end
$var wire 1 ( txready $end
$var wire 1 ) tx_valid $end
$var wire 1 * tx_data_o $end
$var wire 1 + shift_load $end
$var wire 1 , shift_en $end
$var wire 8 - right [7:0] $end
$var wire 1 . piso_o $end
$var wire 1 / parity_o $end
$var wire 1 0 parity_en $end
$var wire 1 1 mux_stop $end
$var wire 1 2 mux_start $end
$var wire 2 3 mux_select [1:0] $end
$var wire 4 4 count_o [3:0] $end
$var wire 1 5 count_enable $end
$var wire 1 6 count_clear $end
$var wire 1 7 baud_tick $end
$var wire 8 8 PISOdata_i [7:0] $end
$var reg 1 9 blue $end
$var reg 1 : green $end
$var reg 8 ; left [7:0] $end
$var reg 1 < red $end
$var reg 1 = rxclk $end
$var reg 8 > ss0 [7:0] $end
$var reg 8 ? ss1 [7:0] $end
$var reg 8 @ ss2 [7:0] $end
$var reg 8 A ss3 [7:0] $end
$var reg 8 B ss4 [7:0] $end
$var reg 8 C ss5 [7:0] $end
$var reg 8 D ss6 [7:0] $end
$var reg 8 E ss7 [7:0] $end
$var reg 1 F txclk $end
$var reg 8 G txdata [7:0] $end
$scope module baud_gen $end
$var wire 1 " clk $end
$var wire 16 H divisor [15:0] $end
$var wire 1 # nrst $end
$var reg 1 7 baud_tick $end
$var reg 1 I baud_tick_n $end
$var reg 16 J counter [15:0] $end
$var reg 16 K counter_n [15:0] $end
$upscope $end
$scope module count0 $end
$var wire 1 " clk $end
$var wire 1 # nrst $end
$var wire 1 5 enable $end
$var wire 1 6 clear $end
$var reg 4 L count [3:0] $end
$var reg 4 M nextCount [3:0] $end
$var reg 1 N overflow_flag $end
$upscope $end
$scope module trans_FSM $end
$var wire 1 7 baud_tick $end
$var wire 1 " clk $end
$var wire 4 O count_data [3:0] $end
$var wire 1 # nrst $end
$var wire 1 0 parity_en $end
$var wire 1 ) tx_valid $end
$var reg 1 6 count_clear $end
$var reg 1 5 count_en $end
$var reg 1 + load $end
$var reg 3 P nextState [2:0] $end
$var reg 2 Q select [1:0] $end
$var reg 1 , shift_en $end
$var reg 1 2 start $end
$var reg 3 R state [2:0] $end
$var reg 1 1 stop $end
$upscope $end
$scope module trans_PISO $end
$var wire 1 " clk $end
$var wire 8 S data_i [7:0] $end
$var wire 1 + load $end
$var wire 1 # nrst $end
$var wire 1 , shift_en $end
$var reg 8 T nextpiso_data [7:0] $end
$var reg 1 U nextpiso_o $end
$var reg 8 V piso_data [7:0] $end
$var reg 1 . piso_o $end
$upscope $end
$scope module trans_mux $end
$var wire 1 . piso_i $end
$var wire 2 W select [1:0] $end
$var wire 1 2 start $end
$var wire 1 1 stop $end
$var wire 1 / parity_i $end
$var reg 1 * tx_data_o $end
$upscope $end
$scope module trans_parity $end
$var wire 8 X data_i [7:0] $end
$var wire 1 0 parity_en $end
$var reg 1 / parity_bit $end
$upscope $end
$upscope $end
$upscope $end
$enddefinitions $end
$comment Show the parameter values. $end
$dumpall
$end
#0
$dumpvars
bx X
b11 W
bx V
xU
bx T
bx S
bx R
b11 Q
b0 P
bx O
xN
bx M
bx L
bx K
bx J
0I
b10011100010 H
bx G
xF
bx E
bx D
bx C
bx B
bx A
bx @
bx ?
bx >
x=
x<
bx ;
x:
x9
bx 8
07
06
05
bx 4
b11 3
02
11
x0
0/
x.
bz1 -
0,
0+
1*
x)
z(
z'
bz &
b0xxxxxxxxxxxxxxxxxxxx %
bx $
1#
1"
bz1 !
$end
#41666
0"
#83332
b0 R
1"
#124998
0"
#166664
1"
#208330
0"
#249996
1"
#291662
0"
#333328
1"
#374994
0"
#416660
1"
#458326
0"
#499992
1"
#500000
b1 K
0U
b0 T
b0 J
b0 V
0.
0#
#541658
0"
#583324
b0 M
b0 4
b0 L
b0 O
1"
#624990
0"
#666656
1"
#708322
0"
#749988
1"
#791654
0"
#833320
1"
#874986
0"
#916652
1"
#958318
0"
#999984
1"
#1000000
1#
#1041650
0"
#1083316
b10 K
b1 J
1"
#1124982
0"
#1166648
b11 K
b10 J
1"
#1208314
0"
#1249980
b100 K
b11 J
1"
#1291646
0"
#1333312
b101 K
b100 J
1"
#1374978
0"
#1416644
b110 K
b101 J
1"
#1458310
0"
#1499976
b111 K
b110 J
1"
#1500000
0)
10
b10100101 8
b10100101 S
b10100101 X
b1xxxxxxxxxx10100101 %
b1xxxxxxxxxx10100101 $
#1541642
0"
#1583308
b1000 K
b111 J
1"
#1624974
0"
#1666640
b1001 K
b1000 J
1"
#1708306
0"
#1749972
b1010 K
b1001 J
1"
#1791638
0"
#1833304
b1011 K
b1010 J
1"
#1874970
0"
#1916636
b1100 K
b1011 J
1"
#1958302
0"
#1999968
b1101 K
b1100 J
1"
#2000000
b1 P
1)
b11xxxxxxxxxx10100101 %
b11xxxxxxxxxx10100101 $
#2041634
0"
#2083300
b10100101 T
b1110 K
b10 P
1+
b1101 J
b1 R
1"
#2100000
1+
0)
b1xxxxxxxxxx10100101 %
b1xxxxxxxxxx10100101 $
#2124966
0"
#2166632
bz0 !
bz0 -
0*
b1111 K
b0 3
b0 Q
b0 W
0+
b1110 J
b10100101 V
b10 R
1"
#2208298
0"
#2249964
b10000 K
b1111 J
1"
#2291630
0"
#2333296
b10001 K
b10000 J
1"
#2374962
0"
#2416628
b10010 K
b10001 J
1"
#2458294
0"
#2499960
b10011 K
b10010 J
1"
#2541626
0"
#2583292
b10100 K
b10011 J
1"
#2624958
0"
#2666624
b10101 K
b10100 J
1"
#2708290
0"
#2749956
b10110 K
b10101 J
1"
#2791622
0"
#2833288
b10111 K
b10110 J
1"
#2874954
0"
#2916620
b11000 K
b10111 J
1"
#2958286
0"
#2999952
b11001 K
b11000 J
1"
#3041618
0"
#3083284
b11010 K
b11001 J
1"
#3124950
0"
#3166616
b11011 K
b11010 J
1"
#3208282
0"
#3249948
b11100 K
b11011 J
1"
#3291614
0"
#3333280
b11101 K
b11100 J
1"
#3374946
0"
#3416612
b11110 K
b11101 J
1"
#3458278
0"
#3499944
b11111 K
b11110 J
1"
#3541610
0"
#3583276
b100000 K
b11111 J
1"
#3624942
0"
#3666608
b100001 K
b100000 J
1"
#3708274
0"
#3749940
b100010 K
b100001 J
1"
#3791606
0"
#3833272
b100011 K
b100010 J
1"
#3874938
0"
#3916604
b100100 K
b100011 J
1"
#3958270
0"
#3999936
b100101 K
b100100 J
1"
#4041602
0"
#4083268
b100110 K
b100101 J
1"
#4124934
0"
#4166600
b100111 K
b100110 J
1"
#4208266
0"
#4249932
b101000 K
b100111 J
1"
#4291598
0"
#4333264
b101001 K
b101000 J
1"
#4374930
0"
#4416596
b101010 K
b101001 J
1"
#4458262
0"
#4499928
b101011 K
b101010 J
1"
#4541594
0"
#4583260
b101100 K
b101011 J
1"
#4624926
0"
#4666592
b101101 K
b101100 J
1"
#4708258
0"
#4749924
b101110 K
b101101 J
1"
#4791590
0"
#4833256
b101111 K
b101110 J
1"
#4874922
0"
#4916588
b110000 K
b101111 J
1"
#4958254
0"
#4999920
b110001 K
b110000 J
1"
#5041586
0"
#5083252
b110010 K
b110001 J
1"
#5124918
0"
#5166584
b110011 K
b110010 J
1"
#5208250
0"
#5249916
b110100 K
b110011 J
1"
#5291582
0"
#5333248
b110101 K
b110100 J
1"
#5374914
0"
#5416580
b110110 K
b110101 J
1"
#5458246
0"
#5499912
b110111 K
b110110 J
1"
#5541578
0"
#5583244
b111000 K
b110111 J
1"
#5624910
0"
#5666576
b111001 K
b111000 J
1"
#5708242
0"
#5749908
b111010 K
b111001 J
1"
#5791574
0"
#5833240
b111011 K
b111010 J
1"
#5874906
0"
#5916572
b111100 K
b111011 J
1"
#5958238
0"
#5999904
b111101 K
b111100 J
1"
#6041570
0"
#6083236
b111110 K
b111101 J
1"
#6124902
0"
#6166568
b111111 K
b111110 J
1"
#6208234
0"
#6249900
b1000000 K
b111111 J
1"
#6291566
0"
#6333232
b1000001 K
b1000000 J
1"
#6374898
0"
#6416564
b1000010 K
b1000001 J
1"
#6458230
0"
#6499896
b1000011 K
b1000010 J
1"
#6541562
0"
#6583228
b1000100 K
b1000011 J
1"
#6624894
0"
#6666560
b1000101 K
b1000100 J
1"
#6708226
0"
#6749892
b1000110 K
b1000101 J
1"
#6791558
0"
#6833224
b1000111 K
b1000110 J
1"
#6874890
0"
#6916556
b1001000 K
b1000111 J
1"
#6958222
0"
#6999888
b1001001 K
b1001000 J
1"
#7041554
0"
#7083220
b1001010 K
b1001001 J
1"
#7124886
0"
#7166552
b1001011 K
b1001010 J
1"
#7208218
0"
#7249884
b1001100 K
b1001011 J
1"
#7291550
0"
#7333216
b1001101 K
b1001100 J
1"
#7374882
0"
#7416548
b1001110 K
b1001101 J
1"
#7458214
0"
#7499880
b1001111 K
b1001110 J
1"
#7541546
0"
#7583212
b1010000 K
b1001111 J
1"
#7624878
0"
#7666544
b1010001 K
b1010000 J
1"
#7708210
0"
#7749876
b1010010 K
b1010001 J
1"
#7791542
0"
#7833208
b1010011 K
b1010010 J
1"
#7874874
0"
#7916540
b1010100 K
b1010011 J
1"
#7958206
0"
#7999872
b1010101 K
b1010100 J
1"
#8041538
0"
#8083204
b1010110 K
b1010101 J
1"
#8124870
0"
#8166536
b1010111 K
b1010110 J
1"
#8208202
0"
#8249868
b1011000 K
b1010111 J
1"
#8291534
0"
#8333200
b1011001 K
b1011000 J
1"
#8374866
0"
#8416532
b1011010 K
b1011001 J
1"
#8458198
0"
#8499864
b1011011 K
b1011010 J
1"
#8541530
0"
#8583196
b1011100 K
b1011011 J
1"
#8624862
0"
#8666528
b1011101 K
b1011100 J
1"
#8708194
0"
#8749860
b1011110 K
b1011101 J
1"
#8791526
0"
#8833192
b1011111 K
b1011110 J
1"
#8874858
0"
#8916524
b1100000 K
b1011111 J
1"
#8958190
0"
#8999856
b1100001 K
b1100000 J
1"
#9041522
0"
#9083188
b1100010 K
b1100001 J
1"
#9124854
0"
#9166520
b1100011 K
b1100010 J
1"
#9208186
0"
#9249852
b1100100 K
b1100011 J
1"
#9291518
0"
#9333184
b1100101 K
b1100100 J
1"
#9374850
0"
#9416516
b1100110 K
b1100101 J
1"
#9458182
0"
#9499848
b1100111 K
b1100110 J
1"
#9541514
0"
#9583180
b1101000 K
b1100111 J
1"
#9624846
0"
#9666512
b1101001 K
b1101000 J
1"
#9708178
0"
#9749844
b1101010 K
b1101001 J
1"
#9791510
0"
#9833176
b1101011 K
b1101010 J
1"
#9874842
0"
#9916508
b1101100 K
b1101011 J
1"
#9958174
0"
#9999840
b1101101 K
b1101100 J
1"
#10041506
0"
#10083172
b1101110 K
b1101101 J
1"
#10124838
0"
#10166504
b1101111 K
b1101110 J
1"
#10208170
0"
#10249836
b1110000 K
b1101111 J
1"
#10291502
0"
#10333168
b1110001 K
b1110000 J
1"
#10374834
0"
#10416500
b1110010 K
b1110001 J
1"
#10458166
0"
#10499832
b1110011 K
b1110010 J
1"
#10541498
0"
#10583164
b1110100 K
b1110011 J
1"
#10624830
0"
#10666496
b1110101 K
b1110100 J
1"
#10708162
0"
#10749828
b1110110 K
b1110101 J
1"
#10791494
0"
#10833160
b1110111 K
b1110110 J
1"
#10874826
0"
#10916492
b1111000 K
b1110111 J
1"
#10958158
0"
#10999824
b1111001 K
b1111000 J
1"
#11041490
0"
#11083156
b1111010 K
b1111001 J
1"
#11124822
0"
#11166488
b1111011 K
b1111010 J
1"
#11208154
0"
#11249820
b1111100 K
b1111011 J
1"
#11291486
0"
#11333152
b1111101 K
b1111100 J
1"
#11374818
0"
#11416484
b1111110 K
b1111101 J
1"
#11458150
0"
#11499816
b1111111 K
b1111110 J
1"
#11541482
0"
#11583148
b10000000 K
b1111111 J
1"
#11624814
0"
#11666480
b10000001 K
b10000000 J
1"
#11708146
0"
#11749812
b10000010 K
b10000001 J
1"
#11791478
0"
#11833144
b10000011 K
b10000010 J
1"
#11874810
0"
#11916476
b10000100 K
b10000011 J
1"
#11958142
0"
#11999808
b10000101 K
b10000100 J
1"
#12041474
0"
#12083140
b10000110 K
b10000101 J
1"
#12124806
0"
#12166472
b10000111 K
b10000110 J
1"
#12208138
0"
#12249804
b10001000 K
b10000111 J
1"
#12291470
0"
#12333136
b10001001 K
b10001000 J
1"
#12374802
0"
#12416468
b10001010 K
b10001001 J
1"
#12458134
0"
#12499800
b10001011 K
b10001010 J
1"
#12541466
0"
#12583132
b10001100 K
b10001011 J
1"
#12624798
0"
#12666464
b10001101 K
b10001100 J
1"
#12708130
0"
#12749796
b10001110 K
b10001101 J
1"
#12791462
0"
#12833128
b10001111 K
b10001110 J
1"
#12874794
0"
#12916460
b10010000 K
b10001111 J
1"
#12958126
0"
#12999792
b10010001 K
b10010000 J
1"
#13041458
0"
#13083124
b10010010 K
b10010001 J
1"
#13124790
0"
#13166456
b10010011 K
b10010010 J
1"
#13208122
0"
#13249788
b10010100 K
b10010011 J
1"
#13291454
0"
#13333120
b10010101 K
b10010100 J
1"
#13374786
0"
#13416452
b10010110 K
b10010101 J
1"
#13458118
0"
#13499784
b10010111 K
b10010110 J
1"
#13541450
0"
#13583116
b10011000 K
b10010111 J
1"
#13624782
0"
#13666448
b10011001 K
b10011000 J
1"
#13708114
0"
#13749780
b10011010 K
b10011001 J
1"
#13791446
0"
#13833112
b10011011 K
b10011010 J
1"
#13874778
0"
#13916444
b10011100 K
b10011011 J
1"
#13958110
0"
#13999776
b10011101 K
b10011100 J
1"
#14041442
0"
#14083108
b10011110 K
b10011101 J
1"
#14124774
0"
#14166440
b10011111 K
b10011110 J
1"
#14208106
0"
#14249772
b10100000 K
b10011111 J
1"
#14291438
0"
#14333104
b10100001 K
b10100000 J
1"
#14374770
0"
#14416436
b10100010 K
b10100001 J
1"
#14458102
0"
#14499768
b10100011 K
b10100010 J
1"
#14541434
0"
#14583100
b10100100 K
b10100011 J
1"
#14624766
0"
#14666432
b10100101 K
b10100100 J
1"
#14708098
0"
#14749764
b10100110 K
b10100101 J
1"
#14791430
0"
#14833096
b10100111 K
b10100110 J
1"
#14874762
0"
#14916428
b10101000 K
b10100111 J
1"
#14958094
0"
#14999760
b10101001 K
b10101000 J
1"
#15041426
0"
#15083092
b10101010 K
b10101001 J
1"
#15124758
0"
#15166424
b10101011 K
b10101010 J
1"
#15208090
0"
#15249756
b10101100 K
b10101011 J
1"
#15291422
0"
#15333088
b10101101 K
b10101100 J
1"
#15374754
0"
#15416420
b10101110 K
b10101101 J
1"
#15458086
0"
#15499752
b10101111 K
b10101110 J
1"
#15541418
0"
#15583084
b10110000 K
b10101111 J
1"
#15624750
0"
#15666416
b10110001 K
b10110000 J
1"
#15708082
0"
#15749748
b10110010 K
b10110001 J
1"
#15791414
0"
#15833080
b10110011 K
b10110010 J
1"
#15874746
0"
#15916412
b10110100 K
b10110011 J
1"
#15958078
0"
#15999744
b10110101 K
b10110100 J
1"
#16041410
0"
#16083076
b10110110 K
b10110101 J
1"
#16124742
0"
#16166408
b10110111 K
b10110110 J
1"
#16208074
0"
#16249740
b10111000 K
b10110111 J
1"
#16291406
0"
#16333072
b10111001 K
b10111000 J
1"
#16374738
0"
#16416404
b10111010 K
b10111001 J
1"
#16458070
0"
#16499736
b10111011 K
b10111010 J
1"
#16541402
0"
#16583068
b10111100 K
b10111011 J
1"
#16624734
0"
#16666400
b10111101 K
b10111100 J
1"
#16708066
0"
#16749732
b10111110 K
b10111101 J
1"
#16791398
0"
#16833064
b10111111 K
b10111110 J
1"
#16874730
0"
#16916396
b11000000 K
b10111111 J
1"
#16958062
0"
#16999728
b11000001 K
b11000000 J
1"
#17041394
0"
#17083060
b11000010 K
b11000001 J
1"
#17124726
0"
#17166392
b11000011 K
b11000010 J
1"
#17208058
0"
#17249724
b11000100 K
b11000011 J
1"
#17291390
0"
#17333056
b11000101 K
b11000100 J
1"
#17374722
0"
#17416388
b11000110 K
b11000101 J
1"
#17458054
0"
#17499720
b11000111 K
b11000110 J
1"
#17541386
0"
#17583052
b11001000 K
b11000111 J
1"
#17624718
0"
#17666384
b11001001 K
b11001000 J
1"
#17708050
0"
#17749716
b11001010 K
b11001001 J
1"
#17791382
0"
#17833048
b11001011 K
b11001010 J
1"
#17874714
0"
#17916380
b11001100 K
b11001011 J
1"
#17958046
0"
#17999712
b11001101 K
b11001100 J
1"
#18041378
0"
#18083044
b11001110 K
b11001101 J
1"
#18124710
0"
#18166376
b11001111 K
b11001110 J
1"
#18208042
0"
#18249708
b11010000 K
b11001111 J
1"
#18291374
0"
#18333040
b11010001 K
b11010000 J
1"
#18374706
0"
#18416372
b11010010 K
b11010001 J
1"
#18458038
0"
#18499704
b11010011 K
b11010010 J
1"
#18541370
0"
#18583036
b11010100 K
b11010011 J
1"
#18624702
0"
#18666368
b11010101 K
b11010100 J
1"
#18708034
0"
#18749700
b11010110 K
b11010101 J
1"
#18791366
0"
#18833032
b11010111 K
b11010110 J
1"
#18874698
0"
#18916364
b11011000 K
b11010111 J
1"
#18958030
0"
#18999696
b11011001 K
b11011000 J
1"
#19041362
0"
#19083028
b11011010 K
b11011001 J
1"
#19124694
0"
#19166360
b11011011 K
b11011010 J
1"
#19208026
0"
#19249692
b11011100 K
b11011011 J
1"
#19291358
0"
#19333024
b11011101 K
b11011100 J
1"
#19374690
0"
#19416356
b11011110 K
b11011101 J
1"
#19458022
0"
#19499688
b11011111 K
b11011110 J
1"
#19541354
0"
#19583020
b11100000 K
b11011111 J
1"
#19624686
0"
#19666352
b11100001 K
b11100000 J
1"
#19708018
0"
#19749684
b11100010 K
b11100001 J
1"
#19791350
0"
#19833016
b11100011 K
b11100010 J
1"
#19874682
0"
#19916348
b11100100 K
b11100011 J
1"
#19958014
0"
#19999680
b11100101 K
b11100100 J
1"
#20041346
0"
#20083012
b11100110 K
b11100101 J
1"
#20124678
0"
#20166344
b11100111 K
b11100110 J
1"
#20208010
0"
#20249676
b11101000 K
b11100111 J
1"
#20291342
0"
#20333008
b11101001 K
b11101000 J
1"
#20374674
0"
#20416340
b11101010 K
b11101001 J
1"
#20458006
0"
#20499672
b11101011 K
b11101010 J
1"
#20541338
0"
#20583004
b11101100 K
b11101011 J
1"
#20624670
0"
#20666336
b11101101 K
b11101100 J
1"
#20708002
0"
#20749668
b11101110 K
b11101101 J
1"
#20791334
0"
#20833000
b11101111 K
b11101110 J
1"
#20874666
0"
#20916332
b11110000 K
b11101111 J
1"
#20957998
0"
#20999664
b11110001 K
b11110000 J
1"
#21041330
0"
#21082996
b11110010 K
b11110001 J
1"
#21124662
0"
#21166328
b11110011 K
b11110010 J
1"
#21207994
0"
#21249660
b11110100 K
b11110011 J
1"
#21291326
0"
#21332992
b11110101 K
b11110100 J
1"
#21374658
0"
#21416324
b11110110 K
b11110101 J
1"
#21457990
0"
#21499656
b11110111 K
b11110110 J
1"
#21541322
0"
#21582988
b11111000 K
b11110111 J
1"
#21624654
0"
#21666320
b11111001 K
b11111000 J
1"
#21707986
0"
#21749652
b11111010 K
b11111001 J
1"
#21791318
0"
#21832984
b11111011 K
b11111010 J
1"
#21874650
0"
#21916316
b11111100 K
b11111011 J
1"
#21957982
0"
#21999648
b11111101 K
b11111100 J
1"
#22041314
0"
#22082980
b11111110 K
b11111101 J
1"
#22124646
0"
#22166312
b11111111 K
b11111110 J
1"
#22207978
0"
#22249644
b100000000 K
b11111111 J
1"
#22291310
0"
#22332976
b100000001 K
b100000000 J
1"
#22374642
0"
#22416308
b100000010 K
b100000001 J
1"
#22457974
0"
#22499640
b100000011 K
b100000010 J
1"
#22541306
0"
#22582972
b100000100 K
b100000011 J
1"
#22624638
0"
#22666304
b100000101 K
b100000100 J
1"
#22707970
0"
#22749636
b100000110 K
b100000101 J
1"
#22791302
0"
#22832968
b100000111 K
b100000110 J
1"
#22874634
0"
#22916300
b100001000 K
b100000111 J
1"
#22957966
0"
#22999632
b100001001 K
b100001000 J
1"
#23041298
0"
#23082964
b100001010 K
b100001001 J
1"
#23124630
0"
#23166296
b100001011 K
b100001010 J
1"
#23207962
0"
#23249628
b100001100 K
b100001011 J
1"
#23291294
0"
#23332960
b100001101 K
b100001100 J
1"
#23374626
0"
#23416292
b100001110 K
b100001101 J
1"
#23457958
0"
#23499624
b100001111 K
b100001110 J
1"
#23541290
0"
#23582956
b100010000 K
b100001111 J
1"
#23624622
0"
#23666288
b100010001 K
b100010000 J
1"
#23707954
0"
#23749620
b100010010 K
b100010001 J
1"
#23791286
0"
#23832952
b100010011 K
b100010010 J
1"
#23874618
0"
#23916284
b100010100 K
b100010011 J
1"
#23957950
0"
#23999616
b100010101 K
b100010100 J
1"
#24041282
0"
#24082948
b100010110 K
b100010101 J
1"
#24124614
0"
#24166280
b100010111 K
b100010110 J
1"
#24207946
0"
#24249612
b100011000 K
b100010111 J
1"
#24291278
0"
#24332944
b100011001 K
b100011000 J
1"
#24374610
0"
#24416276
b100011010 K
b100011001 J
1"
#24457942
0"
#24499608
b100011011 K
b100011010 J
1"
#24541274
0"
#24582940
b100011100 K
b100011011 J
1"
#24624606
0"
#24666272
b100011101 K
b100011100 J
1"
#24707938
0"
#24749604
b100011110 K
b100011101 J
1"
#24791270
0"
#24832936
b100011111 K
b100011110 J
1"
#24874602
0"
#24916268
b100100000 K
b100011111 J
1"
