src/baud_generator.sv
module baud_generator(
    input clk, nrst,
    output baud_tick
);
    logic [15:0] counter, divisor, counter_n;
    logic baud_tick_n;
    
    //baud rate currently set to 9600, hwclk is 12MHz
    //divisor = clock_Frequency / baud_Rate

    //change divisor value to change baud rate
    assign divisor = 16'd1250;

    always_ff @(posedge clk, negedge rst_n) begin
        if (~rst_n) begin
            counter   <= 16'd0;
            baud_tick <= 1'b0;
        end else begin
            counter <= counter_n;
            baud_tick <= baud_tick_n;
        end
    end

    always_comb begin
        if(counter == (divisor - 16'd1)) begin
            counter_n = 16'd0;
            baud_tick_n = 1'b1;
        end else begin
            counter_n = counter + 16'd1;
            baud_tick = 1'b0;
        end
    end

endmodule

source/transmitterMux.sv
module transmitterMux(
    input logic piso_i, start, stop, parity_i,
    input logic [1:0] select,
    output logic tx_data_o
);
    always_comb begin
        if(select == 2'b00) begin
            tx_data_o = start;
        end else if (select == 2'b01) begin
            tx_data_o = piso_i;
        end else if (select == 2'b10) begin
            tx_data_o = parity_i;
        end else begin //select =  11
            tx_data_o = stop; 
        end
    end

endmodule

src/transmitter_parityGen.sv
// Transmitter Parity Generator
// Anna Dalton (https://github.com/annazdalton)

module transmitter_parityGen();
    input logic [7:0] data_i,
    input logic parity_en;
    output logic parity_bit

//even parity
always_comb begin
        if (parity_en) begin
            //XOR reduction for parity bit
            parity_bit = ^ data_i;
        end else begin
            parity_bit = 1'b0;
        end
    end
endmodule

src/transmitter_PISO.sv
// Transmitter Parallel In Serial Out Module (Shift Register w/ Parallel Load)
// Anna Dalton (https://github.com/annazdalton)

module transmitter_PISO(
    input clk, nrst,
    input logic [7:0] data_i,
    input logic shift_en, load,
    output logic piso_o
);
    logic [7:0] piso_data, nextpiso_data;

    always_ff @(posedge clk, negedge nrst) begin
        if (~nrst) begin
            piso_data <= '0;
        end else begin
            piso_data <= nextpiso_data;
        end
    end

    //shift register logic, parallel load has priority 
    //LSB gets sent out first
    always_comb begin
        if(load) begin
            nextpiso_data = data_i;
        end else if (shift_en) begin
            nextpiso_data = {1'b0, piso_data[7:1]};
        end else begin
            nextpiso_data = piso_data;
        end
    end

    assign piso_o = piso_data[0];

endmodule

src/transmitter_FSM.sv
module transmitter_FSM(
    input logic clk, nrst, baud_tick, tx_valid, parity_en,
    input logic [3:0] count_data,
    output logic start, stop, count_en, count_clear, shift_en, load,
    output logic [1:0] select
);

    // typedef enum logic [2:0]{  
    //     IDLE = 0,
    //     LOAD = 1,
    //     START = 2,
    //     DATA = 3,
    //     PARITY = 4,
    //     STOP = 5
    // } state_t;

    //state_t state, nextState;
    logic [2:0] state, nextState;

    always_ff @(posedge clk, negedge nrst) begin
        if(~nrst) begin
            state <= '0; //idle
        end else begin
            state <= nextState;
        end
    end

    always_comb begin
        //defaults to prevent latch
        nextState = state;

        count_en = 1'b0;
        count_clear = 1'b0;

        start = 1'b0;
        stop = 1'b1;

        select = 2'b11;
        load = 1'b0;
        shift_en = 1'b0;

        case(state) 
            3'b0: begin 
                select = 2'b11; // stop/idle
                
                if(tx_valid) begin
                    nextState = 3'd1;
                end else begin
                    nextState = 3'd0;
                end
            end
            3'd1: begin
                load = 1'b1;
                select = 2'b11;
                nextState = 3'd2;
            end
            3'd2: begin 
                select = 2'b00; //send start bit to rx

                if(baud_tick) begin
                    nextState = 3'd3;
                    count_clear = 1'b1; //clear count before data state
                end else begin
                    nextState = 3'd2;
                end
            end
            3'd3: begin 
                //send data serially output from PISO
                select = 2'b01;

                if(baud_tick) begin
                    shift_en = 1'b1;
                    count_en = 1'b1;
                    //if done counting
                    if(count_data == 4'd7) begin
                        //reset counter
                        count_en = 1'b0;
                        count_clear = 1'b1;
                        if(parity_en) begin
                            nextState = 3'd4;
                        end else begin
                            nextState = 3'd5;
                        end
                    end else begin
                        nextState = 3'd3; //keep sending data out
                    end
                end
            end
            3'd4: begin 
                select = 2'b10; //parity output via mux

                if(baud_tick) begin
                    nextState = 3'd5;
                end else begin
                    nextState = 3'd4;
                end
            end
            3'd5: begin 
                select = 2'b11; // send stop to rx

                if(baud_tick) begin
                    nextState = 3'd0;
                end else begin
                    nextState = 3'd5;
                end
            end
            default: begin
                nextState = '0; 
            end
        endcase
    end
endmodule

source/counter.sv
// counter, counts to 8 for transmitter FSM
// Anna Dalton (https://github.com/annazdalton)

module counter(
    input logic clk, nrst, enable, clear,
    output logic [3:0] count,
    output logic overflow_flag
);
    logic [3:0] nextCount;

    always_ff @(posedge clk, negedge ~nrst) begin
        if(~nrst) begin
            count <= '0;
        end else begin
            count <= nextCount;
        end
    end

    always_comb begin
        if(clear) begin
            nextCount = '0;
        end else if(enable) begin
            nextCount = count + 4'd1; 
            //overflow flag is high if count > 8
            if(count == 4'd8) begin
                overflow_flag = 1'b1; 
            end else begin
                overflow_flag = 1'b0;
            end
        end else begin
            nextCount = count;
        end
    end
endmodule

source/transmitter_top.sv
module transmitter_top (
  // I/O ports
  input  logic hwclk, reset, //hwclk = 10 MHz
  input  logic [20:0] pb,
  output logic [7:0] left, right,
         ss7, ss6, ss5, ss4, ss3, ss2, ss1, ss0,
  output logic red, green, blue,

  // UART ports
  output logic [7:0] txdata,
  input  logic [7:0] rxdata,
  output logic txclk, rxclk,
  input  logic txready, rxready
);


logic [7:0] PISOdata_i;
logic [3:0] count_o;
logic [1:0] mux_select;
logic count_enable, count_clear, count_overflow, piso_o, tx_data_o, mux_stop, mux_start, parity_o, tx_valid, parity_en, shift_en, shift_load, baud_tick;

// data going into transmitter is PB[7:0] of FPGA
assign PISOdata_i = pb[7:0];
// data coming out is shown on RIGHT[0]
assign right[0] = tx_data_o;
assign right[1] = parity_en;
assign right[2] = tx_valid;
assign right[3] = baud_tick;
//user inputs
assign tx_valid = pb[19];
assign parity_en = pb[18];

counter count0(
  .clk(hwclk), 
  .nrst(reset), 
  .enable(count_enable), 
  .clear(count_clear), 
  .count(count_o), 
  .overflow_flag()
);

transmitter_FSM trans_FSM(
  //inputs
  .clk(hwclk),
  .nrst(reset),
  .baud_tick(baud_tick),
  .tx_valid(tx_valid),
  .parity_en(parity_en),
  .count_data(count_o),
  //outputs
  .start(mux_start),
  .stop(mux_stop),
  .count_en(count_enable),
  .count_clear(count_clear),
  .shift_en(shift_en),
  .load(shift_load),
  .select(mux_select)
);

transmitter_PISO trans_PISO(
  .clk(hwclk),
  .nrst(reset),
  .data_i(PISOdata_i),
  .shift_en(shift_en),
  .load(shift_load),
  .piso_o(piso_o)
);

transmitter_parityGen trans_parity(
  .data_i(PISOdata_i),
  .parity_en(parity_en),
  .parity_bit(parity_o)
);

transmitterMux trans_mux(
  .piso_i(piso_o),
  .start(mux_start),
  .stop(mux_stop),
  .parity_i(parity_o),
  .select(mux_select),
  .tx_data_o(tx_data_o)
);

baud_generator baud_gen(
  .clk(hwclk),
  .nrst(reset),
  .baud_tick(baud_tick)
);

endmodule

testbench/transmitter_top_tb.sv
`timescale 1ns / 1ps

module transmitter_top_tb();

logic clk, nrst;
logic [19:0] pb;
logic [7:0] right;

transmitter_top topTest(
    .hwclk(clk),
    .reset(nrst),
    .pb(pb),
    .left(),
    .right(right),
    .ss7(),
    .ss6(),
    .ss5(),
    .ss4(),
    .ss3(),
    .ss2(),
    .ss1(),
    .ss0(),
    .txdata(),
    .rxdata(),
    .txclk(),
    .rxclk(),
    .txready(),
    .rxready()
);

//12MHz clk - period is 83.33 ns
always begin
    #41.66
    clk = ~clk;
end

initial begin
    $dumpfile("transmitter_top.vcd");
    $dumpvars(0, transmitter_top_tb);
    clk = 0;

    //reset
    nrst = 1;
    pb = '0;
    #500
    nrst = 0;
    #500
    nrst = 1;
    #500

    pb[7:0] = 8'b10100101;

    // parity_en on pb[18], tx_valid on pb[19]
    pb[18]    = 1'b0; // 0 = no parity, 1 = enable parity
    pb[19]    = 1'b0;

    //assert tx_valid for one clock
    #500;
    pb[19]    = 1'b1; // tx_valid pulse
    #100;
    pb[19]    = 1'b0;

    #2_000_000; // 2 ms in ns
    $finish;
end
endmodule

waves/transmitter_top.vcd
$date
	Mon Dec  1 11:46:08 2025
$end
$version
	Icarus Verilog
$end
$timescale
	1ps
$end
$scope module transmitter_top_tb $end
$var wire 8 ! right [7:0] $end
$var reg 1 " clk $end
$var reg 1 # nrst $end
$var reg 20 $ pb [19:0] $end
$scope module topTest $end
$var wire 1 " hwclk $end
$var wire 21 % pb [20:0] $end
$var wire 1 # reset $end
$var wire 8 & rxdata [7:0] $end
$var wire 1 ' rxready $end
$var wire 1 ( txready $end
$var wire 1 ) tx_valid $end
$var wire 1 * tx_data_o $end
$var wire 1 + shift_load $end
$var wire 1 , shift_en $end
$var wire 8 - right [7:0] $end
$var wire 1 . piso_o $end
$var wire 1 / parity_o $end
$var wire 1 0 parity_en $end
$var wire 1 1 mux_stop $end
$var wire 1 2 mux_start $end
$var wire 2 3 mux_select [1:0] $end
$var wire 4 4 count_o [3:0] $end
$var wire 1 5 count_enable $end
$var wire 1 6 count_clear $end
$var wire 1 7 baud_tick $end
$var wire 8 8 PISOdata_i [7:0] $end
$var reg 1 9 blue $end
$var reg 1 : green $end
$var reg 8 ; left [7:0] $end
$var reg 1 < red $end
$var reg 1 = rxclk $end
$var reg 8 > ss0 [7:0] $end
$var reg 8 ? ss1 [7:0] $end
$var reg 8 @ ss2 [7:0] $end
$var reg 8 A ss3 [7:0] $end
$var reg 8 B ss4 [7:0] $end
$var reg 8 C ss5 [7:0] $end
$var reg 8 D ss6 [7:0] $end
$var reg 8 E ss7 [7:0] $end
$var reg 1 F txclk $end
$var reg 8 G txdata [7:0] $end
$scope module baud_gen $end
$var wire 1 " clk $end
$var wire 16 H divisor [15:0] $end
$var wire 1 # nrst $end
$var reg 1 7 baud_tick $end
$var reg 1 I baud_tick_n $end
$var reg 16 J counter [15:0] $end
$var reg 16 K counter_n [15:0] $end
$upscope $end
$scope module count0 $end
$var wire 1 " clk $end
$var wire 1 # nrst $end
$var wire 1 5 enable $end
$var wire 1 6 clear $end
$var reg 4 L count [3:0] $end
$var reg 4 M nextCount [3:0] $end
$var reg 1 N overflow_flag $end
$upscope $end
$scope module trans_FSM $end
$var wire 1 7 baud_tick $end
$var wire 1 " clk $end
$var wire 4 O count_data [3:0] $end
$var wire 1 # nrst $end
$var wire 1 0 parity_en $end
$var wire 1 ) tx_valid $end
$var reg 1 6 count_clear $end
$var reg 1 5 count_en $end
$var reg 1 + load $end
$var reg 3 P nextState [2:0] $end
$var reg 2 Q select [1:0] $end
$var reg 1 , shift_en $end
$var reg 1 2 start $end
$var reg 3 R state [2:0] $end
$var reg 1 1 stop $end
$upscope $end
$scope module trans_PISO $end
$var wire 1 " clk $end
$var wire 8 S data_i [7:0] $end
$var wire 1 + load $end
$var wire 1 # nrst $end
$var wire 1 , shift_en $end
$var wire 1 . piso_o $end
$var reg 8 T nextpiso_data [7:0] $end
$var reg 8 U piso_data [7:0] $end
$upscope $end
$scope module trans_mux $end
$var wire 1 . piso_i $end
$var wire 2 V select [1:0] $end
$var wire 1 2 start $end
$var wire 1 1 stop $end
$var wire 1 / parity_i $end
$var reg 1 * tx_data_o $end
$upscope $end
$scope module trans_parity $end
$var wire 8 W data_i [7:0] $end
$var wire 1 0 parity_en $end
$var reg 1 / parity_bit $end
$upscope $end
$upscope $end
$upscope $end
$enddefinitions $end
$comment Show the parameter values. $end
$dumpall
$end
#0
$dumpvars
b0 W
b11 V
bx U
bx T
b0 S
bx R
b11 Q
b0 P
bx O
xN
bx M
bx L
bx K
bx J
0I
b10011100010 H
bx G
xF
bx E
bx D
bx C
bx B
bx A
bx @
bx ?
bx >
x=
x<
bx ;
x:
x9
b0 8
x7
06
05
bx 4
b11 3
02
11
00
0/
x.
bz1 -
0,
0+
1*
0)
z(
z'
bz &
b0 %
b0 $
1#
0"
bz1 !
$end
#41660
b0 R
07
1"
#83320
0"
#124980
1"
#166640
0"
#208300
1"
#249960
0"
#291620
1"
#333280
0"
#374940
1"
#416600
0"
#458260
1"
#499920
0"
#500000
b0 T
0.
b1 K
b0 U
b0 J
0#
#541580
b0 M
b0 4
b0 L
b0 O
1"
#583240
0"
#624900
1"
#666560
0"
#708220
1"
#749880
0"
#791540
1"
#833200
0"
#874860
1"
#916520
0"
#958180
1"
#999840
0"
#1000000
1#
#1041500
b10 K
b1 J
1"
#1083160
0"
#1124820
b11 K
b10 J
1"
#1166480
0"
#1208140
b100 K
b11 J
1"
#1249800
0"
#1291460
b101 K
b100 J
1"
#1333120
0"
#1374780
b110 K
b101 J
1"
#1416440
0"
#1458100
b111 K
b110 J
1"
#1499760
0"
#1500000
10
b10100101 8
b10100101 S
b10100101 W
b1000000000010100101 %
b1000000000010100101 $
#1541420
b1000 K
b111 J
1"
#1583080
0"
#1624740
b1001 K
b1000 J
1"
#1666400
0"
#1708060
b1010 K
b1001 J
1"
#1749720
0"
#1791380
b1011 K
b1010 J
1"
#1833040
0"
#1874700
b1100 K
b1011 J
1"
#1916360
0"
#1958020
b1101 K
b1100 J
1"
#1999680
0"
#2000000
b1 P
1)
b11000000000010100101 %
b11000000000010100101 $
#2041340
b10100101 T
b1110 K
b10 P
1+
b1101 J
b1 R
1"
#2083000
0"
#2100000
1+
b10 P
0)
b1000000000010100101 %
b1000000000010100101 $
#2124660
bz0 !
bz0 -
0*
b0 3
b0 Q
b0 V
0+
1.
b1111 K
b10 R
b10100101 U
b1110 J
1"
#2166320
0"
#2207980
b10000 K
b1111 J
1"
#2249640
0"
#2291300
b10001 K
b10000 J
1"
#2332960
0"
#2374620
b10010 K
b10001 J
1"
#2416280
0"
#2457940
b10011 K
b10010 J
1"
#2499600
0"
#2541260
b10100 K
b10011 J
1"
#2582920
0"
#2624580
b10101 K
b10100 J
1"
#2666240
0"
#2707900
b10110 K
b10101 J
1"
#2749560
0"
#2791220
b10111 K
b10110 J
1"
#2832880
0"
#2874540
b11000 K
b10111 J
1"
#2916200
0"
#2957860
b11001 K
b11000 J
1"
#2999520
0"
#3041180
b11010 K
b11001 J
1"
#3082840
0"
#3124500
b11011 K
b11010 J
1"
#3166160
0"
#3207820
b11100 K
b11011 J
1"
#3249480
0"
#3291140
b11101 K
b11100 J
1"
#3332800
0"
#3374460
b11110 K
b11101 J
1"
#3416120
0"
#3457780
b11111 K
b11110 J
1"
#3499440
0"
#3541100
b100000 K
b11111 J
1"
#3582760
0"
#3624420
b100001 K
b100000 J
1"
#3666080
0"
#3707740
b100010 K
b100001 J
1"
#3749400
0"
#3791060
b100011 K
b100010 J
1"
#3832720
0"
#3874380
b100100 K
b100011 J
1"
#3916040
0"
#3957700
b100101 K
b100100 J
1"
#3999360
0"
#4041020
b100110 K
b100101 J
1"
#4082680
0"
#4124340
b100111 K
b100110 J
1"
#4166000
0"
#4207660
b101000 K
b100111 J
1"
#4249320
0"
#4290980
b101001 K
b101000 J
1"
#4332640
0"
#4374300
b101010 K
b101001 J
1"
#4415960
0"
#4457620
b101011 K
b101010 J
1"
#4499280
0"
#4540940
b101100 K
b101011 J
1"
#4582600
0"
#4624260
b101101 K
b101100 J
1"
#4665920
0"
#4707580
b101110 K
b101101 J
1"
#4749240
0"
#4790900
b101111 K
b101110 J
1"
#4832560
0"
#4874220
b110000 K
b101111 J
1"
#4915880
0"
#4957540
b110001 K
b110000 J
1"
#4999200
0"
#5040860
b110010 K
b110001 J
1"
#5082520
0"
#5124180
b110011 K
b110010 J
1"
#5165840
0"
#5207500
b110100 K
b110011 J
1"
#5249160
0"
#5290820
b110101 K
b110100 J
1"
#5332480
0"
#5374140
b110110 K
b110101 J
1"
#5415800
0"
#5457460
b110111 K
b110110 J
1"
#5499120
0"
#5540780
b111000 K
b110111 J
1"
#5582440
0"
#5624100
b111001 K
b111000 J
1"
#5665760
0"
#5707420
b111010 K
b111001 J
1"
#5749080
0"
#5790740
b111011 K
b111010 J
1"
#5832400
0"
#5874060
b111100 K
b111011 J
1"
#5915720
0"
#5957380
b111101 K
b111100 J
1"
#5999040
0"
#6040700
b111110 K
b111101 J
1"
#6082360
0"
#6124020
b111111 K
b111110 J
1"
#6165680
0"
#6207340
b1000000 K
b111111 J
1"
#6249000
0"
#6290660
b1000001 K
b1000000 J
1"
#6332320
0"
#6373980
b1000010 K
b1000001 J
1"
#6415640
0"
#6457300
b1000011 K
b1000010 J
1"
#6498960
0"
#6540620
b1000100 K
b1000011 J
1"
#6582280
0"
#6623940
b1000101 K
b1000100 J
1"
#6665600
0"
#6707260
b1000110 K
b1000101 J
1"
#6748920
0"
#6790580
b1000111 K
b1000110 J
1"
#6832240
0"
#6873900
b1001000 K
b1000111 J
1"
#6915560
0"
#6957220
b1001001 K
b1001000 J
1"
#6998880
0"
#7040540
b1001010 K
b1001001 J
1"
#7082200
0"
#7123860
b1001011 K
b1001010 J
1"
#7165520
0"
#7207180
b1001100 K
b1001011 J
1"
#7248840
0"
#7290500
b1001101 K
b1001100 J
1"
#7332160
0"
#7373820
b1001110 K
b1001101 J
1"
#7415480
0"
#7457140
b1001111 K
b1001110 J
1"
#7498800
0"
#7540460
b1010000 K
b1001111 J
1"
#7582120
0"
#7623780
b1010001 K
b1010000 J
1"
#7665440
0"
#7707100
b1010010 K
b1010001 J
1"
#7748760
0"
#7790420
b1010011 K
b1010010 J
1"
#7832080
0"
#7873740
b1010100 K
b1010011 J
1"
#7915400
0"
#7957060
b1010101 K
b1010100 J
1"
#7998720
0"
#8040380
b1010110 K
b1010101 J
1"
#8082040
0"
#8123700
b1010111 K
b1010110 J
1"
#8165360
0"
#8207020
b1011000 K
b1010111 J
1"
#8248680
0"
#8290340
b1011001 K
b1011000 J
1"
#8332000
0"
#8373660
b1011010 K
b1011001 J
1"
#8415320
0"
#8456980
b1011011 K
b1011010 J
1"
#8498640
0"
#8540300
b1011100 K
b1011011 J
1"
#8581960
0"
#8623620
b1011101 K
b1011100 J
1"
#8665280
0"
#8706940
b1011110 K
b1011101 J
1"
#8748600
0"
#8790260
b1011111 K
b1011110 J
1"
#8831920
0"
#8873580
b1100000 K
b1011111 J
1"
#8915240
0"
#8956900
b1100001 K
b1100000 J
1"
#8998560
0"
#9040220
b1100010 K
b1100001 J
1"
#9081880
0"
#9123540
b1100011 K
b1100010 J
1"
#9165200
0"
#9206860
b1100100 K
b1100011 J
1"
#9248520
0"
#9290180
b1100101 K
b1100100 J
1"
#9331840
0"
#9373500
b1100110 K
b1100101 J
1"
#9415160
0"
#9456820
b1100111 K
b1100110 J
1"
#9498480
0"
#9540140
b1101000 K
b1100111 J
1"
#9581800
0"
#9623460
b1101001 K
b1101000 J
1"
#9665120
0"
#9706780
b1101010 K
b1101001 J
1"
#9748440
0"
#9790100
b1101011 K
b1101010 J
1"
#9831760
0"
#9873420
b1101100 K
b1101011 J
1"
#9915080
0"
#9956740
b1101101 K
b1101100 J
1"
#9998400
0"
#10040060
b1101110 K
b1101101 J
1"
#10081720
0"
#10123380
b1101111 K
b1101110 J
1"
#10165040
0"
#10206700
b1110000 K
b1101111 J
1"
#10248360
0"
#10290020
b1110001 K
b1110000 J
1"
#10331680
0"
#10373340
b1110010 K
b1110001 J
1"
#10415000
0"
#10456660
b1110011 K
b1110010 J
1"
#10498320
0"
#10539980
b1110100 K
b1110011 J
1"
#10581640
0"
#10623300
b1110101 K
b1110100 J
1"
#10664960
0"
#10706620
b1110110 K
b1110101 J
1"
#10748280
0"
#10789940
b1110111 K
b1110110 J
1"
#10831600
0"
#10873260
b1111000 K
b1110111 J
1"
#10914920
0"
#10956580
b1111001 K
b1111000 J
1"
#10998240
0"
#11039900
b1111010 K
b1111001 J
1"
#11081560
0"
#11123220
b1111011 K
b1111010 J
1"
#11164880
0"
#11206540
b1111100 K
b1111011 J
1"
#11248200
0"
#11289860
b1111101 K
b1111100 J
1"
#11331520
0"
#11373180
b1111110 K
b1111101 J
1"
#11414840
0"
#11456500
b1111111 K
b1111110 J
1"
#11498160
0"
#11539820
b10000000 K
b1111111 J
1"
#11581480
0"
#11623140
b10000001 K
b10000000 J
1"
#11664800
0"
#11706460
b10000010 K
b10000001 J
1"
#11748120
0"
#11789780
b10000011 K
b10000010 J
1"
#11831440
0"
#11873100
b10000100 K
b10000011 J
1"
#11914760
0"
#11956420
b10000101 K
b10000100 J
1"
#11998080
0"
#12039740
b10000110 K
b10000101 J
1"
#12081400
0"
#12123060
b10000111 K
b10000110 J
1"
#12164720
0"
#12206380
b10001000 K
b10000111 J
1"
#12248040
0"
#12289700
b10001001 K
b10001000 J
1"
#12331360
0"
#12373020
b10001010 K
b10001001 J
1"
#12414680
0"
#12456340
b10001011 K
b10001010 J
1"
#12498000
0"
#12539660
b10001100 K
b10001011 J
1"
#12581320
0"
#12622980
b10001101 K
b10001100 J
1"
#12664640
0"
#12706300
b10001110 K
b10001101 J
1"
#12747960
0"
#12789620
b10001111 K
b10001110 J
1"
#12831280
0"
#12872940
b10010000 K
b10001111 J
1"
#12914600
0"
#12956260
b10010001 K
b10010000 J
1"
#12997920
0"
#13039580
b10010010 K
b10010001 J
1"
#13081240
0"
#13122900
b10010011 K
b10010010 J
1"
#13164560
0"
#13206220
b10010100 K
b10010011 J
1"
#13247880
0"
#13289540
b10010101 K
b10010100 J
1"
#13331200
0"
#13372860
b10010110 K
b10010101 J
1"
#13414520
0"
#13456180
b10010111 K
b10010110 J
1"
#13497840
0"
#13539500
b10011000 K
b10010111 J
1"
#13581160
0"
#13622820
b10011001 K
b10011000 J
1"
#13664480
0"
#13706140
b10011010 K
b10011001 J
1"
#13747800
0"
#13789460
b10011011 K
b10011010 J
1"
#13831120
0"
#13872780
b10011100 K
b10011011 J
1"
#13914440
0"
#13956100
b10011101 K
b10011100 J
1"
#13997760
0"
#14039420
b10011110 K
b10011101 J
1"
#14081080
0"
#14122740
b10011111 K
b10011110 J
1"
#14164400
0"
#14206060
b10100000 K
b10011111 J
1"
#14247720
0"
#14289380
b10100001 K
b10100000 J
1"
#14331040
0"
#14372700
b10100010 K
b10100001 J
1"
#14414360
0"
#14456020
b10100011 K
b10100010 J
1"
#14497680
0"
#14539340
b10100100 K
b10100011 J
1"
#14581000
0"
#14622660
b10100101 K
b10100100 J
1"
#14664320
0"
#14705980
b10100110 K
b10100101 J
1"
#14747640
0"
#14789300
b10100111 K
b10100110 J
1"
#14830960
0"
#14872620
b10101000 K
b10100111 J
1"
#14914280
0"
#14955940
b10101001 K
b10101000 J
1"
#14997600
0"
#15039260
b10101010 K
b10101001 J
1"
#15080920
0"
#15122580
b10101011 K
b10101010 J
1"
#15164240
0"
#15205900
b10101100 K
b10101011 J
1"
#15247560
0"
#15289220
b10101101 K
b10101100 J
1"
#15330880
0"
#15372540
b10101110 K
b10101101 J
1"
#15414200
0"
#15455860
b10101111 K
b10101110 J
1"
#15497520
0"
#15539180
b10110000 K
b10101111 J
1"
#15580840
0"
#15622500
b10110001 K
b10110000 J
1"
#15664160
0"
#15705820
b10110010 K
b10110001 J
1"
#15747480
0"
#15789140
b10110011 K
b10110010 J
1"
#15830800
0"
#15872460
b10110100 K
b10110011 J
1"
#15914120
0"
#15955780
b10110101 K
b10110100 J
1"
#15997440
0"
#16039100
b10110110 K
b10110101 J
1"
#16080760
0"
#16122420
b10110111 K
b10110110 J
1"
#16164080
0"
#16205740
b10111000 K
b10110111 J
1"
#16247400
0"
#16289060
b10111001 K
b10111000 J
1"
#16330720
0"
#16372380
b10111010 K
b10111001 J
1"
#16414040
0"
#16455700
b10111011 K
b10111010 J
1"
#16497360
0"
#16539020
b10111100 K
b10111011 J
1"
#16580680
0"
#16622340
b10111101 K
b10111100 J
1"
#16664000
0"
#16705660
b10111110 K
b10111101 J
1"
#16747320
0"
#16788980
b10111111 K
b10111110 J
1"
#16830640
0"
#16872300
b11000000 K
b10111111 J
1"
#16913960
0"
#16955620
b11000001 K
b11000000 J
1"
#16997280
0"
#17038940
b11000010 K
b11000001 J
1"
#17080600
0"
#17122260
b11000011 K
b11000010 J
1"
#17163920
0"
#17205580
b11000100 K
b11000011 J
1"
#17247240
0"
#17288900
b11000101 K
b11000100 J
1"
#17330560
0"
#17372220
b11000110 K
b11000101 J
1"
#17413880
0"
#17455540
b11000111 K
b11000110 J
1"
#17497200
0"
#17538860
b11001000 K
b11000111 J
1"
#17580520
0"
#17622180
b11001001 K
b11001000 J
1"
#17663840
0"
#17705500
b11001010 K
b11001001 J
1"
#17747160
0"
#17788820
b11001011 K
b11001010 J
1"
#17830480
0"
#17872140
b11001100 K
b11001011 J
1"
#17913800
0"
#17955460
b11001101 K
b11001100 J
1"
#17997120
0"
#18038780
b11001110 K
b11001101 J
1"
#18080440
0"
#18122100
b11001111 K
b11001110 J
1"
#18163760
0"
#18205420
b11010000 K
b11001111 J
1"
#18247080
0"
#18288740
b11010001 K
b11010000 J
1"
#18330400
0"
#18372060
b11010010 K
b11010001 J
1"
#18413720
0"
#18455380
b11010011 K
b11010010 J
1"
#18497040
0"
#18538700
b11010100 K
b11010011 J
1"
#18580360
0"
#18622020
b11010101 K
b11010100 J
1"
#18663680
0"
#18705340
b11010110 K
b11010101 J
1"
#18747000
0"
#18788660
b11010111 K
b11010110 J
1"
#18830320
0"
#18871980
b11011000 K
b11010111 J
1"
#18913640
0"
#18955300
b11011001 K
b11011000 J
1"
#18996960
0"
#19038620
b11011010 K
b11011001 J
1"
#19080280
0"
#19121940
b11011011 K
b11011010 J
1"
#19163600
0"
#19205260
b11011100 K
b11011011 J
1"
#19246920
0"
#19288580
b11011101 K
b11011100 J
1"
#19330240
0"
#19371900
b11011110 K
b11011101 J
1"
#19413560
0"
#19455220
b11011111 K
b11011110 J
1"
#19496880
0"
#19538540
b11100000 K
b11011111 J
1"
#19580200
0"
#19621860
b11100001 K
b11100000 J
1"
#19663520
0"
#19705180
b11100010 K
b11100001 J
1"
#19746840
0"
#19788500
b11100011 K
b11100010 J
1"
#19830160
0"
#19871820
b11100100 K
b11100011 J
1"
#19913480
0"
#19955140
b11100101 K
b11100100 J
1"
#19996800
0"
#20038460
b11100110 K
b11100101 J
1"
#20080120
0"
#20121780
b11100111 K
b11100110 J
1"
#20163440
0"
#20205100
b11101000 K
b11100111 J
1"
#20246760
0"
#20288420
b11101001 K
b11101000 J
1"
#20330080
0"
#20371740
b11101010 K
b11101001 J
1"
#20413400
0"
#20455060
b11101011 K
b11101010 J
1"
#20496720
0"
#20538380
b11101100 K
b11101011 J
1"
#20580040
0"
#20621700
b11101101 K
b11101100 J
1"
#20663360
0"
#20705020
b11101110 K
b11101101 J
1"
#20746680
0"
#20788340
b11101111 K
b11101110 J
1"
#20830000
0"
#20871660
b11110000 K
b11101111 J
1"
#20913320
0"
#20954980
b11110001 K
b11110000 J
1"
#20996640
0"
#21038300
b11110010 K
b11110001 J
1"
#21079960
0"
#21121620
b11110011 K
b11110010 J
1"
#21163280
0"
#21204940
b11110100 K
b11110011 J
1"
#21246600
0"
#21288260
b11110101 K
b11110100 J
1"
#21329920
0"
#21371580
b11110110 K
b11110101 J
1"
#21413240
0"
#21454900
b11110111 K
b11110110 J
1"
#21496560
0"
#21538220
b11111000 K
b11110111 J
1"
#21579880
0"
#21621540
b11111001 K
b11111000 J
1"
#21663200
0"
#21704860
b11111010 K
b11111001 J
1"
#21746520
0"
#21788180
b11111011 K
b11111010 J
1"
#21829840
0"
#21871500
b11111100 K
b11111011 J
1"
#21913160
0"
#21954820
b11111101 K
b11111100 J
1"
#21996480
0"
#22038140
b11111110 K
b11111101 J
1"
#22079800
0"
#22121460
b11111111 K
b11111110 J
1"
#22163120
0"
#22204780
b100000000 K
b11111111 J
1"
#22246440
0"
#22288100
b100000001 K
b100000000 J
1"
#22329760
0"
#22371420
b100000010 K
b100000001 J
1"
#22413080
0"
#22454740
b100000011 K
b100000010 J
1"
#22496400
0"
#22538060
b100000100 K
b100000011 J
1"
#22579720
0"
#22621380
b100000101 K
b100000100 J
1"
#22663040
0"
#22704700
b100000110 K
b100000101 J
1"
#22746360
0"
#22788020
b100000111 K
b100000110 J
1"
#22829680
0"
#22871340
b100001000 K
b100000111 J
1"
#22913000
0"
#22954660
b100001001 K
b100001000 J
1"
#22996320
0"
#23037980
b100001010 K
b100001001 J
1"
#23079640
0"
#23121300
b100001011 K
b100001010 J
1"
#23162960
0"
#23204620
b100001100 K
b100001011 J
1"
#23246280
0"
#23287940
b100001101 K
b100001100 J
1"
#23329600
0"
#23371260
b100001110 K
b100001101 J
1"
#23412920
0"
#23454580
b100001111 K
b100001110 J
1"
#23496240
0"
#23537900
b100010000 K
b100001111 J
1"
#23579560
0"
#23621220
b100010001 K
b100010000 J
1"
#23662880
0"
#23704540
b100010010 K
b100010001 J
1"
#23746200
0"
#23787860
b100010011 K
b100010010 J
1"
#23829520
0"
#23871180
b100010100 K
b100010011 J
1"
#23912840
0"
#23954500
b100010101 K
b100010100 J
1"
#23996160
0"
#24037820
b100010110 K
b100010101 J
1"
#24079480
0"
#24121140
b100010111 K
b100010110 J
1"
#24162800
0"
#24204460
b100011000 K
b100010111 J
1"
#24246120
0"
#24287780
b100011001 K
b100011000 J
1"
#24329440
0"
#24371100
b100011010 K
b100011001 J
1"
#24412760
0"
#24454420
b100011011 K
b100011010 J
1"
#24496080
0"
#24537740
b100011100 K
b100011011 J
1"
#24579400
0"
#24621060
b100011101 K
b100011100 J
1"
#24662720
0"
#24704380
b100011110 K
b100011101 J
1"
#24746040
0"
#24787700
b100011111 K
b100011110 J
1"
#24829360
0"
#24871020
b100100000 K
b100011111 J
1"
#24912680
0"
#24954340
b100100001 K
b100100000 J
1"
#24996000
0"
#25037660
b100100010 K
b100100001 J
1"
#25079320
0"
#25120980
b100100011 K
b100100010 J
1"
#25162640
0"
#25204300
b100100100 K
b100100011 J
1"
#25245960
0"
#25287620
b100100101 K
b100100100 J
1"
